interactive_mcp_server/__init__.py
interactive_mcp_server/__main__.py
interactive_mcp_server/debug.py
interactive_mcp_server/i18n.py
interactive_mcp_server/py.typed
interactive_mcp_server/server.py
interactive_mcp_server/desktop_app/__init__.py
interactive_mcp_server/desktop_app/desktop_app.py
interactive_mcp_server/desktop_release/__init__.py
interactive_mcp_server/desktop_release/interactive-mcp-server-desktop-linux
interactive_mcp_server/desktop_release/interactive-mcp-server-desktop-macos-arm64
interactive_mcp_server/desktop_release/interactive-mcp-server-desktop-macos-intel
interactive_mcp_server/desktop_release/interactive-mcp-server-desktop.exe
interactive_mcp_server/desktop_release/mcp-feedback-enhanced-desktop-linux
interactive_mcp_server/desktop_release/mcp-feedback-enhanced-desktop-macos-arm64
interactive_mcp_server/desktop_release/mcp-feedback-enhanced-desktop-macos-intel
interactive_mcp_server/desktop_release/mcp-feedback-enhanced-desktop.exe
interactive_mcp_server/utils/__init__.py
interactive_mcp_server/utils/error_handler.py
interactive_mcp_server/utils/memory_monitor.py
interactive_mcp_server/utils/resource_manager.py
interactive_mcp_server/web/__init__.py
interactive_mcp_server/web/main.py
interactive_mcp_server/web/constants/__init__.py
interactive_mcp_server/web/constants/message_codes.py
interactive_mcp_server/web/locales/en/translation.json
interactive_mcp_server/web/locales/zh-CN/translation.json
interactive_mcp_server/web/locales/zh-TW/translation.json
interactive_mcp_server/web/models/__init__.py
interactive_mcp_server/web/models/feedback_result.py
interactive_mcp_server/web/models/feedback_session.py
interactive_mcp_server/web/routes/__init__.py
interactive_mcp_server/web/routes/main_routes.py
interactive_mcp_server/web/static/favicon.ico
interactive_mcp_server/web/static/icon-192.png
interactive_mcp_server/web/static/icon.svg
interactive_mcp_server/web/static/index.html
interactive_mcp_server/web/static/css/audio-management.css
interactive_mcp_server-2.7.5.dist-info/METADATA
interactive_mcp_server-2.7.5.dist-info/WHEEL
interactive_mcp_server-2.7.5.dist-info/entry_points.txt
interactive_mcp_server-2.7.5.dist-info/licenses/LICENSE
interactive_mcp_server-2.7.5.dist-info/RECORD
